{"cameraMode":{"drawMode":0,"name":"Shaded","section":"Shading Mode"},"sceneLighting":false,"audioPlay":false,"sceneViewState":{"showFog":true,"showMaterialUpdate":false,"showSkybox":false,"showFlares":true,"showImageEffects":true,"showParticleSystems":true},"in2DMode":false,"pivot":{"x":212.92617797851563,"y":101.53427124023438,"z":-113.45465087890625},"rotation":{"x":-0.05475345626473427,"y":0.16015969216823579,"z":0.008898094296455384,"w":0.9855341911315918},"size":176.5740966796875,"orthographic":false}